papr_memory/__init__.py
papr_memory/_base_client.py
papr_memory/_cleanup.py
papr_memory/_client.py
papr_memory/_compat.py
papr_memory/_constants.py
papr_memory/_exceptions.py
papr_memory/_files.py
papr_memory/_logging.py
papr_memory/_model_cache.py
papr_memory/_models.py
papr_memory/_parse_integration.py
papr_memory/_qs.py
papr_memory/_resource.py
papr_memory/_response.py
papr_memory/_retrieval_logging.py
papr_memory/_streaming.py
papr_memory/_types.py
papr_memory/_uninstall.py
papr_memory/_version.py
papr_memory/py.typed
papr_memory/_utils/__init__.py
papr_memory/_utils/_compat.py
papr_memory/_utils/_datetime_parse.py
papr_memory/_utils/_logs.py
papr_memory/_utils/_proxy.py
papr_memory/_utils/_reflection.py
papr_memory/_utils/_resources_proxy.py
papr_memory/_utils/_streams.py
papr_memory/_utils/_sync.py
papr_memory/_utils/_transform.py
papr_memory/_utils/_typing.py
papr_memory/_utils/_utils.py
papr_memory/lib/.keep
papr_memory/resources/__init__.py
papr_memory/resources/document.py
papr_memory/resources/feedback.py
papr_memory/resources/graphql.py
papr_memory/resources/memory.py
papr_memory/resources/schemas.py
papr_memory/resources/user.py
papr_memory/types/__init__.py
papr_memory/types/add_memory_param.py
papr_memory/types/add_memory_response.py
papr_memory/types/auto_graph_generation_param.py
papr_memory/types/batch_memory_response.py
papr_memory/types/batch_response.py
papr_memory/types/context_item.py
papr_memory/types/context_item_param.py
papr_memory/types/document_cancel_processing_response.py
papr_memory/types/document_get_status_response.py
papr_memory/types/document_upload_params.py
papr_memory/types/document_upload_response.py
papr_memory/types/feedback_request_param.py
papr_memory/types/feedback_response.py
papr_memory/types/feedback_submit_batch_params.py
papr_memory/types/feedback_submit_params.py
papr_memory/types/graph_generation_param.py
papr_memory/types/manual_graph_generation_param.py
papr_memory/types/memory_add_batch_params.py
papr_memory-2.18.0.dist-info/METADATA
papr_memory-2.18.0.dist-info/WHEEL
papr_memory-2.18.0.dist-info/entry_points.txt
papr_memory-2.18.0.dist-info/licenses/LICENSE
papr_memory-2.18.0.dist-info/RECORD
