Metadata-Version: 2.3
Name: papr_memory
Version: 2.18.0
Summary: The official Python library for the Papr API
Project-URL: Homepage, https://github.com/Papr-ai/papr-pythonSDK
Project-URL: Repository, https://github.com/Papr-ai/papr-pythonSDK
Author-email: Papr <support@papr.ai>
License: Apache-2.0
Classifier: Intended Audience :: Developers
Classifier: License :: OSI Approved :: Apache Software License
Classifier: Operating System :: MacOS
Classifier: Operating System :: Microsoft :: Windows
Classifier: Operating System :: OS Independent
Classifier: Operating System :: POSIX
Classifier: Operating System :: POSIX :: Linux
Classifier: Programming Language :: Python :: 3.9
Classifier: Programming Language :: Python :: 3.10
Classifier: Programming Language :: Python :: 3.11
Classifier: Programming Language :: Python :: 3.12
Classifier: Programming Language :: Python :: 3.13
Classifier: Programming Language :: Python :: 3.14
Classifier: Topic :: Software Development :: Libraries :: Python Modules
Classifier: Typing :: Typed
Requires-Python: >=3.9
Requires-Dist: anyio<5,>=3.5.0
Requires-Dist: chromadb>=0.4.0
Requires-Dist: distro<2,>=1.7.0
Requires-Dist: httpx<1,>=0.23.0
Requires-Dist: psutil>=5.8.0
Requires-Dist: pydantic<3,>=2.7
Requires-Dist: sentence-transformers>=2.0.0
Requires-Dist: sniffio
Requires-Dist: typing-extensions<5,>=4.10
Provides-Extra: aiohttp
Requires-Dist: aiohttp; extra == 'aiohttp'
Requires-Dist: httpx-aiohttp>=0.1.9; extra == 'aiohttp'
Provides-Extra: coreml
Requires-Dist: coremltools>=7.0; extra == 'coreml'
Requires-Dist: huggingface-hub>=0.20.0; extra == 'coreml'
Requires-Dist: torch==2.5.*; extra == 'coreml'
Requires-Dist: transformers>=4.44; extra == 'coreml'
Provides-Extra: mlx
Requires-Dist: mlx-lm>=0.28.2; extra == 'mlx'
